README.md
setup.py
memtools/__init__.py
memtools.egg-info/PKG-INFO
memtools.egg-info/SOURCES.txt
memtools.egg-info/dependency_links.txt
memtools.egg-info/top_level.txt