Metadata-Version: 2.1
Name: memtools
Version: 2.0.0
Summary: python module
Home-page: https://github.com/memtools/
Author: memtools
Author-email: gymk@gaypan.jp
Classifier: Programming Language :: Python :: 3
Classifier: Operating System :: OS Independent
Requires-Python: >=3.6
